AUTHORS
ChangeLog
LICENSE
README.md
requirements.txt
setup.cfg
setup.py
tox.ini
klugman/__init__.py
klugman/base.py
klugman/jsonutil.py
klugman/klugman.py
klugman/v1.py
klugman.egg-info/PKG-INFO
klugman.egg-info/SOURCES.txt
klugman.egg-info/dependency_links.txt
klugman.egg-info/entry_points.txt
klugman.egg-info/not-zip-safe
klugman.egg-info/pbr.json
klugman.egg-info/requires.txt
klugman.egg-info/top_level.txt