Metadata-Version: 1.1
Name: klugman
Version: 0.5.dev25
Summary: StackTach.v3 Client
Home-page: https://github.com/StackTach/klugman
Author: Dark Secret Software Inc.
Author-email: admin@darksecretsoftware.com
License: Apache-2
Keywords: stacktach
Platform: UNKNOWN
Classifier: Development Status :: 3 - Alpha
Classifier: Environment :: Console
Classifier: Intended Audience :: Developers
Classifier: Intended Audience :: Information Technology
Classifier: License :: OSI Approved :: Apache Software License
Classifier: Operating System :: OS Independent
Classifier: Programming Language :: Python
Classifier: Topic :: Software Development :: Libraries :: Python Modules
